yfmcp/__init__.py
yfmcp/chart.py
yfmcp/py.typed
yfmcp/server.py
yfmcp/types.py
yfmcp-0.8.0.dist-info/METADATA
yfmcp-0.8.0.dist-info/WHEEL
yfmcp-0.8.0.dist-info/entry_points.txt
yfmcp-0.8.0.dist-info/licenses/LICENSE
yfmcp-0.8.0.dist-info/RECORD
