Metadata-Version: 2.4
Name: yfmcp
Version: 0.8.0
Author-email: narumi <toucans-cutouts0f@icloud.com>
License-File: LICENSE
Requires-Python: >=3.12
Requires-Dist: loguru>=0.7.3
Requires-Dist: mcp[cli]>=1.6.0
Requires-Dist: mplfinance>=0.12.9
Requires-Dist: tabulate>=0.9.0
Requires-Dist: yfinance>=1.0
